odoo/addons/stock_location_warehouse/README.rst
odoo/addons/stock_location_warehouse/__init__.py
odoo/addons/stock_location_warehouse/__manifest__.py
odoo/addons/stock_location_warehouse/i18n/it.po
odoo/addons/stock_location_warehouse/i18n/stock_location_warehouse.pot
odoo/addons/stock_location_warehouse/models/__init__.py
odoo/addons/stock_location_warehouse/models/stock_location.py
odoo/addons/stock_location_warehouse/readme/CONFIGURE.rst
odoo/addons/stock_location_warehouse/readme/CONTRIBUTORS.rst
odoo/addons/stock_location_warehouse/readme/DESCRIPTION.rst
odoo/addons/stock_location_warehouse/readme/USAGE.rst
odoo/addons/stock_location_warehouse/static/description/icon.png
odoo/addons/stock_location_warehouse/static/description/index.html
odoo/addons/stock_location_warehouse/tests/__init__.py
odoo/addons/stock_location_warehouse/tests/test_location_warehouse.py
odoo/addons/stock_location_warehouse/views/stock_location.xml
odoo14_addon_stock_location_warehouse-14.0.1.1.0.dist-info/METADATA
odoo14_addon_stock_location_warehouse-14.0.1.1.0.dist-info/WHEEL
odoo14_addon_stock_location_warehouse-14.0.1.1.0.dist-info/top_level.txt
odoo14_addon_stock_location_warehouse-14.0.1.1.0.dist-info/RECORD
